greetings_helloworld2030_3/__init__.py
greetings_helloworld2030_3/Listing18_1.py
greetings_helloworld2030_3-0.1.0.dist-info/METADATA
greetings_helloworld2030_3-0.1.0.dist-info/WHEEL
greetings_helloworld2030_3-0.1.0.dist-info/RECORD
