Metadata-Version: 2.3
Name: greetings_helloworld2030_3
Version: 0.1.0
Summary: project description
Author: Fabio Nelli
Author-email:  meccanismo.complesso@gmail.com
Requires-Python: >=3.8,<4.0
Classifier: Programming Language :: Python :: 3
Classifier: Programming Language :: Python :: 3.8
Classifier: Programming Language :: Python :: 3.9
Classifier: Programming Language :: Python :: 3.10
Classifier: Programming Language :: Python :: 3.11
Classifier: Programming Language :: Python :: 3.12
Classifier: Programming Language :: Python :: 3.13
